Week 5/verilog/avsddac.v
module avsddac(
	OUT, 
	D, 
	VREFH, 
	VREFL
);
   output OUT;
   input VREFH;
   input VREFL;
   input[9:0] D;

   reg real OUT;
   wire real VREFH;
   wire real VREFL;
   wire real VSS, VDD;
   real NaN;
   wire EN;

   wire [10:0] Dext;
   assign Dext = {1'b0, D};
   assign EN = 1;

   initial begin
      NaN = 0.0/0.0;
      if (EN == 1'b0) begin
         OUT <= 0;
      end else if (VREFH == NaN) begin
         OUT <= NaN;
      end else if (VREFL == NaN) begin
         OUT <= NaN;
      end else if (EN == 1'b1) begin
         OUT <= VREFL + ($itor(Dext) / 1023.0)*(VREFH - VREFL);
      end else begin
         OUT <= NaN;
      end

   end

   always @(D or EN or VREFH or VREFL) begin
      if (EN == 1'b0) begin
         OUT <= 0;
      end else if (VREFH == NaN) begin
         OUT <= NaN;
      end else if (VREFL == NaN) begin
         OUT <= NaN;
      end else if (EN == 1'b1) begin
         OUT <= VREFL + ($itor(Dext) / 1023.0)*(VREFH - VREFL);
      end else begin
         OUT <= NaN;
      end
   end

endmodule

Week 5/verilog/avsddac_tb.v
`timescale 1ns / 1ps

module avsddac_tb;

   reg EN;
   reg real VREFL, VREFH;
   reg [9:0] D;
   wire real OUT;

   avsddac dut (.OUT(OUT), .VREFL(VREFL), .VREFH(VREFH), .D(D));
   
   initial begin
      EN = 1'b0;
      #5 EN = 1'b1;
   end

   initial begin
      VREFH = 3.3;
      VREFL = 0.0;
   end

   initial begin
      #10 D = 10'h3FF;
      #10 D = 10'h1DB;
      #10 D = 10'h3FE;
      #10 D = 10'h3FA;
      #10 D = 10'h0A1;
      #10 D = 10'h000;
      #10 D = 10'h25F;
   end

   initial begin
      $dumpfile("tb_vsddac.vcd");
      $dumpvars(0, avsddac_tb);

      #300 $finish;
   end
endmodule

Week 5/verilog/tb_vsddac.vcd
$date
	Sun May  1 16:53:58 2022
$end
$version
	Icarus Verilog
$end
$timescale
	1ps
$end
$scope module avsddac_tb $end
$var reg 10 ! D [9:0] $end
$var reg 1 " EN $end
$var real 1 # VREFH $end
$var real 1 $ VREFL $end
$var real 1 % OUT $end
$scope module dut $end
$var wire 10 & D [9:0] $end
$var wire 1 ' EN $end
$var wire 11 ( Dext [10:0] $end
$var real 1 ) NaN $end
$var real 1 * OUT $end
$var real 1 + VREFH $end
$var real 1 , VREFL $end
$upscope $end
$upscope $end
$enddefinitions $end
#0
$dumpvars
r0 ,
r3.3 +
r0 *
rnan )
b0xxxxxxxxxx (
1'
bx &
r0 %
r0 $
r3.3 #
0"
bx !
$end
#5000
1"
#10000
r3.3 %
r3.3 *
b1111111111 (
b1111111111 !
b1111111111 &
#20000
r1.532258064516129 %
r1.532258064516129 *
b111011011 (
b111011011 !
b111011011 &
#30000
r3.296774193548387 %
r3.296774193548387 *
b1111111110 (
b1111111110 !
b1111111110 &
#40000
r3.283870967741935 %
r3.283870967741935 *
b1111111010 (
b1111111010 !
b1111111010 &
#50000
r0.5193548387096774 %
r0.5193548387096774 *
b10100001 (
b10100001 !
b10100001 &
#60000
r0 %
r0 *
b0 (
b0 !
b0 &
#70000
r1.958064516129032 %
r1.958064516129032 *
b1001011111 (
b1001011111 !
b1001011111 &
