Week 4/verilog/avsdpll.v
`timescale 1ns / 1ps
module avsd_pll_1v8( CLK, VCO_IN, VDDA, VDDD, VSSA, VSSD, EN_VCO, REF);

  input VSSD;
  input EN_VCO;
  input VSSA;
  input VDDD;
  input VDDA;
  input VCO_IN;
  output CLK;
  input REF;
  
  reg CLK;
  real period, lastedge, refpd;
  wire  VSSD, VSSA, VDDD, VDDA;
 

  initial begin
     lastedge = 0.0;
     period = 25.0; // 25ns period = 40MHz
     CLK <= 0;
  end

  // Toggle clock at rate determined by period
  always @(CLK or EN_VCO) begin
     if (EN_VCO == 1'b1) begin
        #(period / 2.0);
        CLK <= (CLK === 1'b0);
     end else if (EN_VCO == 1'b0) begin
        CLK <= 1'b0;
     end else begin
        CLK <= 1'bx;
     end
  end
   
  // Update period on every reference rising edge
  always @(posedge REF) begin
     if (lastedge > 0.0) begin
     refpd = $realtime - lastedge;
        // Adjust period towards 1/8 the reference period
        //period = (0.99 * period) + (0.01 * (refpd / 8.0));
        period =  (refpd / 8.0) ;
     end
     lastedge = $realtime;
  end
endmodule

Week 4/verilog/pll_tb.v
`timescale 1ns / 1ps
module pll_tb();

  reg VSSD;
  reg EN_VCO;

  reg VSSA;
  reg VDDD;
  reg VDDA;
  reg VCO_IN;
  reg REF;

  wire CLK;

  avsd_pll_1v8 dut(CLK, VCO_IN, VDDA, VDDD, VSSA, VSSD, EN_VCO, REF);

  initial begin
    {REF, EN_VCO} = 0;
    VCO_IN = 1'b0;
    VDDA = 1.8;
    VDDD = 1.8;
    VSSA = 0;
    VSSD = 0;
  end
  
  initial begin
    $dumpfile("tb_pll_check.vcd");
    $dumpvars(0, pll_tb);
  end

  initial begin
    repeat(400)
    begin
      EN_VCO = 1;
      #100 REF = ~REF;
      #(83.33/2) VCO_IN = ~VCO_IN;
    end

    $finish;
  end

endmodule

Week 4/verilog/tb_pll.vcd
$date
	Sun Apr 24 09:26:07 2022
$end
$version
	Icarus Verilog
$end
$timescale
	1ps
$end
$scope module pll_tb $end
$var wire 1 ! CLK $end
$var reg 1 " EN_VCO $end
$var reg 1 # REF $end
$var reg 1 $ VCO_IN $end
$var reg 1 % VDDA $end
$var reg 1 & VDDD $end
$var reg 1 ' VSSA $end
$var reg 1 ( VSSD $end
$scope module dut $end
$var wire 1 " EN_VCO $end
$var wire 1 # REF $end
$var wire 1 $ VCO_IN $end
$var wire 1 % VDDA $end
$var wire 1 & VDDD $end
$var wire 1 ' VSSA $end
$var wire 1 ( VSSD $end
$var reg 1 ! CLK $end
$var real 1 ) lastedge $end
$var real 1 * period $end
$var real 1 + refpd $end
$upscope $end
$upscope $end
$enddefinitions $end
#0
$dumpvars
r0 +
r25 *
r0 )
0(
0'
0&
0%
0$
0#
1"
0!
$end
#12500
1!
#25000
0!
#37500
1!
#50000
0!
#62500
1!
#75000
0!
#87500
1!
#100000
0!
r100 )
1#
#112500
1!
#125000
0!
#137500
1!
#141665
1$
#150000
0!
#162500
1!
#175000
0!
#187500
1!
#200000
0!
#212500
1!
#225000
0!
#237500
1!
#241665
0#
#250000
0!
#262500
1!
#275000
0!
#283330
0$
#287500
1!
#300000
0!
#312500
1!
#325000
0!
#337500
1!
#350000
0!
#362500
1!
#375000
0!
#383330
r383.33 )
r35.41625 *
r283.33 +
1#
#387500
1!
#405208
0!
#422916
1!
#424995
1$
#440624
0!
#458332
1!
#476040
0!
#493748
1!
#511456
0!
#524995
0#
#529164
1!
#546872
0!
#564580
1!
#566660
0$
#582288
0!
#599996
1!
#617704
0!
#635412
1!
#653120
0!
#666660
r666.66 )
1#
#670828
1!
#688536
0!
#706244
1!
#708325
1$
#723952
0!
#741660
1!
#759368
0!
#777076
1!
#794784
0!
#808325
0#
#812492
1!
#830200
0!
#847908
1!
#849990
0$
#865616
0!
#883324
1!
#901032
0!
#918740
1!
#936448
0!
#949990
r949.99 )
r35.41625000000001 *
r283.33 +
1#
#954156
1!
#971864
0!
#989572
1!
#991655
1$
#1007280
0!
#1024988
1!
#1042696
0!
#1060404
1!
#1078112
0!
#1091655
0#
#1095820
1!
#1113528
0!
#1131236
1!
#1133320
0$
#1148944
0!
#1166652
1!
#1184360
0!
#1202068
1!
#1219776
0!
#1233320
r1233.32 )
r35.41624999999999 *
r283.3299999999999 +
1#
#1237484
1!
#1255192
0!
#1272900
1!
#1274985
1$
#1290608
0!
#1308316
1!
#1326024
0!
#1343732
1!
#1361440
0!
#1374985
0#
#1379148
1!
#1396856
0!
#1414564
1!
#1416650
0$
#1432272
0!
#1449980
1!
#1467688
0!
#1485396
1!
#1503104
0!
#1516650
r1516.65 )
r35.41625000000002 *
r283.3300000000002 +
1#
#1520812
1!
#1538520
0!
#1556228
1!
#1558315
1$
#1573936
0!
#1591644
1!
#1609352
0!
#1627060
1!
#1644768
0!
#1658315
0#
#1662476
1!
#1680184
0!
#1697892
1!
#1699980
0$
#1715600
0!
#1733308
1!
#1751016
0!
#1768724
1!
#1786432
0!
#1799980
r1799.98 )
r35.41624999999999 *
r283.3299999999999 +
1#
#1804140
1!
#1821848
0!
#1839556
1!
#1841645
1$
#1857264
0!
#1874972
1!
#1892680
0!
#1910388
1!
#1928096
0!
#1941645
0#
#1945804
1!
#1963512
0!
#1981220
1!
#1983310
0$
#1998928
0!
#2016636
1!
#2034344
0!
#2052052
1!
#2069760
0!
#2083310
r2083.31 )
1#
#2087468
1!
#2105176
0!
#2122884
1!
#2124975
1$
#2140592
0!
#2158300
1!
#2176008
0!
#2193716
1!
#2211424
0!
#2224975
0#
#2229132
1!
#2246840
0!
#2264548
1!
#2266640
0$
#2282256
0!
#2299964
1!
#2317672
0!
#2335380
1!
#2353088
0!
#2366640
r2366.64 )
1#
#2370796
1!
#2388504
0!
#2406212
1!
#2408305
1$
#2423920
0!
#2441628
1!
#2459336
0!
#2477044
1!
#2494752
0!
#2508305
0#
#2512460
1!
#2530168
0!
#2547876
1!
#2549970
0$
#2565584
0!
#2583292
1!
#2601000
0!
#2618708
1!
#2636416
0!
#2649970
r2649.97 )
1#
#2654124
1!
#2671832
0!
#2689540
1!
#2691635
1$
#2707248
0!
#2724956
1!
#2742664
0!
#2760372
1!
#2778080
0!
#2791635
0#
#2795788
1!
#2813496
0!
#2831204
1!
#2833300
0$
#2848912
0!
#2866620
1!
#2884328
0!
#2902036
1!
#2919744
0!
#2933300
r2933.3 )
r35.41625000000005 *
r283.3300000000004 +
1#
#2937452
1!
#2955160
0!
#2972868
1!
#2974965
1$
#2990576
0!
#3008284
1!
#3025992
0!
#3043700
1!
#3061408
0!
#3074965
0#
#3079116
1!
#3096824
0!
#3114532
1!
#3116630
0$
#3132240
0!
#3149948
1!
#3167656
0!
#3185364
1!
#3203072
0!
#3216630
r3216.63 )
r35.41624999999999 *
r283.3299999999999 +
1#
#3220780
1!
#3238488
0!
#3256196
1!
#3258295
1$
#3273904
0!
#3291612
1!
#3309320
0!
#3327028
1!
#3344736
0!
#3358295
0#
#3362444
1!
#3380152
0!
#3397860
1!
#3399960
0$
#3415568
0!
#3433276
1!
#3450984
0!
#3468692
1!
#3486400
0!
#3499960
r3499.96 )
1#
#3504108
1!
#3521816
0!
#3539524
1!
#3541625
1$
#3557232
0!
#3574940
1!
#3592648
0!
#3610356
1!
#3628064
0!
#3641625
0#
#3645772
1!
#3663480
0!
#3681188
1!
#3683290
0$
#3698896
0!
#3716604
1!
#3734312
0!
#3752020
1!
#3769728
0!
#3783290
r3783.29 )
1#
#3787436
1!
#3805144
0!
#3822852
1!
#3824955
1$
#3840560
0!
#3858268
1!
#3875976
0!
#3893684
1!
#3911392
0!
#3924955
0#
#3929100
1!
#3946808
0!
#3964516
1!
#3966620
0$
#3982224
0!
#3999932
1!
#4017640
0!
#4035348
1!
#4053056
0!
#4066620
r4066.62 )
1#
#4070764
1!
#4088472
0!
#4106180
1!
#4108285
1$
#4123888
0!
#4141596
1!
#4159304
0!
#4177012
1!
#4194720
0!
#4208285
0#
#4212428
1!
#4230136
0!
#4247844
1!
#4249950
0$
#4265552
0!
#4283260
1!
#4300968
0!
#4318676
1!
#4336384
0!
#4349950
r4349.95 )
1#
#4354092
1!
#4371800
0!
#4389508
1!
#4391615
1$
#4407216
0!
#4424924
1!
#4442632
0!
#4460340
1!
#4478048
0!
#4491615
0#
#4495756
1!
#4513464
0!
#4531172
1!
#4533280
0$
#4548880
0!
#4566588
1!
#4584296
0!
#4602004
1!
#4619712
0!
#4633280
r4633.28 )
1#
#4637420
1!
#4655128
0!
#4672836
1!
#4674945
1$
#4690544
0!
#4708252
1!
#4725960
0!
#4743668
1!
#4761376
0!
#4774945
0#
#4779084
1!
#4796792
0!
#4814500
1!
#4816610
0$
#4832208
0!
#4849916
1!
#4867624
0!
#4885332
1!
#4903040
0!
#4916610
r4916.61 )
1#
#4920748
1!
#4938456
0!
#4956164
1!
#4958275
1$
#4973872
0!
#4991580
1!
#5009288
0!
#5026996
1!
#5044704
0!
#5058275
0#
#5062412
1!
#5080120
0!
#5097828
1!
#5099940
0$
#5115536
0!
#5133244
1!
#5150952
0!
#5168660
1!
#5186368
0!
#5199940
r5199.94 )
1#
#5204076
1!
#5221784
0!
#5239492
1!
#5241605
1$
#5257200
0!
#5274908
1!
#5292616
0!
#5310324
1!
#5328032
0!
#5341605
0#
#5345740
1!
#5363448
0!
#5381156
1!
#5383270
0$
#5398864
0!
#5416572
1!
#5434280
0!
#5451988
1!
#5469696
0!
#5483270
r5483.27 )
r35.4162500000001 *
r283.3300000000008 +
1#
#5487404
1!
#5505112
0!
#5522820
1!
#5524935
1$
#5540528
0!
#5558236
1!
#5575944
0!
#5593652
1!
#5611360
0!
#5624935
0#
#5629068
1!
#5646776
0!
#5664484
1!
#5666600
0$
#5682192
0!
#5699900
1!
#5717608
0!
#5735316
1!
#5753024
0!
#5766600
r5766.6 )
r35.41624999999999 *
r283.3299999999999 +
1#
#5770732
1!
#5788440
0!
#5806148
1!
#5808265
1$
#5823856
0!
#5841564
1!
#5859272
0!
#5876980
1!
#5894688
0!
#5908265
0#
#5912396
1!
#5930104
0!
#5947812
1!
#5949930
0$
#5965520
0!
#5983228
1!
#6000936
0!
#6018644
1!
#6036352
0!
#6049930
r6049.93 )
1#
#6054060
1!
#6071768
0!
#6089476
1!
#6091595
1$
#6107184
0!
#6124892
1!
#6142600
0!
#6160308
1!
#6178016
0!
#6191595
0#
#6195724
1!
#6213432
0!
#6231140
1!
#6233260
0$
#6248848
0!
#6266556
1!
#6284264
0!
#6301972
1!
#6319680
0!
#6333260
r6333.26 )
1#
#6337388
1!
#6355096
0!
#6372804
1!
#6374925
1$
#6390512
0!
#6408220
1!
#6425928
0!
#6443636
1!
#6461344
0!
#6474925
0#
#6479052
1!
#6496760
0!
#6514468
1!
#6516590
0$
#6532176
0!
#6549884
1!
#6567592
0!
#6585300
1!
#6603008
0!
#6616590
r6616.59 )
1#
#6620716
1!
#6638424
0!
#6656132
1!
#6658255
1$
#6673840
0!
#6691548
1!
#6709256
0!
#6726964
1!
#6744672
0!
#6758255
0#
#6762380
1!
#6780088
0!
#6797796
1!
#6799920
0$
#6815504
0!
#6833212
1!
#6850920
0!
#6868628
1!
#6886336
0!
#6899920
r6899.92 )
1#
#6904044
1!
#6921752
0!
#6939460
1!
#6941585
1$
#6957168
0!
#6974876
1!
#6992584
0!
#7010292
1!
#7028000
0!
#7041585
0#
#7045708
1!
#7063416
0!
#7081124
1!
#7083250
0$
#7098832
0!
#7116540
1!
#7134248
0!
#7151956
1!
#7169664
0!
#7183250
r7183.25 )
1#
#7187372
1!
#7205080
0!
#7222788
1!
#7224915
1$
#7240496
0!
#7258204
1!
#7275912
0!
#7293620
1!
#7311328
0!
#7324915
0#
#7329036
1!
#7346744
0!
#7364452
1!
#7366580
0$
#7382160
0!
#7399868
1!
#7417576
0!
#7435284
1!
#7452992
0!
#7466580
r7466.58 )
1#
#7470700
1!
#7488408
0!
#7506116
1!
#7508245
1$
#7523824
0!
#7541532
1!
#7559240
0!
#7576948
1!
#7594656
0!
#7608245
0#
#7612364
1!
#7630072
0!
#7647780
1!
#7649910
0$
#7665488
0!
#7683196
1!
#7700904
0!
#7718612
1!
#7736320
0!
#7749910
r7749.91 )
1#
#7754028
1!
#7771736
0!
#7789444
1!
#7791575
1$
#7807152
0!
#7824860
1!
#7842568
0!
#7860276
1!
#7877984
0!
#7891575
0#
#7895692
1!
#7913400
0!
#7931108
1!
#7933240
0$
#7948816
0!
#7966524
1!
#7984232
0!
#8001940
1!
#8019648
0!
#8033240
r8033.24 )
1#
#8037356
1!
#8055064
0!
#8072772
1!
#8074905
1$
#8090480
0!
#8108188
1!
#8125896
0!
#8143604
1!
#8161312
0!
#8174905
0#
#8179020
1!
#8196728
0!
#8214436
1!
#8216570
0$
#8232144
0!
#8249852
1!
#8267560
0!
#8285268
1!
#8302976
0!
#8316570
r8316.57 )
1#
#8320684
1!
#8338392
0!
#8356100
1!
#8358235
1$
#8373808
0!
#8391516
1!
#8409224
0!
#8426932
1!
#8444640
0!
#8458235
0#
#8462348
1!
#8480056
0!
#8497764
1!
#8499900
0$
#8515472
0!
#8533180
1!
#8550888
0!
#8568596
1!
#8586304
0!
#8599900
r8599.9 )
1#
#8604012
1!
#8621720
0!
#8639428
1!
#8641565
1$
#8657136
0!
#8674844
1!
#8692552
0!
#8710260
1!
#8727968
0!
#8741565
0#
#8745676
1!
#8763384
0!
#8781092
1!
#8783230
0$
#8798800
0!
#8816508
1!
#8834216
0!
#8851924
1!
#8869632
0!
#8883230
r8883.23 )
1#
#8887340
1!
#8905048
0!
#8922756
1!
#8924895
1$
#8940464
0!
#8958172
1!
#8975880
0!
#8993588
1!
#9011296
0!
#9024895
0#
#9029004
1!
#9046712
0!
#9064420
1!
#9066560
0$
#9082128
0!
#9099836
1!
#9117544
0!
#9135252
1!
#9152960
0!
#9166560
r9166.559999999999 )
1#
#9170668
1!
#9188376
0!
#9206084
1!
#9208225
1$
#9223792
0!
#9241500
1!
#9259208
0!
#9276916
1!
#9294624
0!
#9308225
0#
#9312332
1!
#9330040
0!
#9347748
1!
#9349890
0$
#9365456
0!
#9383164
1!
#9400872
0!
#9418580
1!
#9436288
0!
#9449890
r9449.889999999999 )
1#
#9453996
1!
#9471704
0!
#9489412
1!
#9491555
1$
#9507120
0!
#9524828
1!
#9542536
0!
#9560244
1!
#9577952
0!
#9591555
0#
#9595660
1!
#9613368
0!
#9631076
1!
#9633220
0$
#9648784
0!
#9666492
1!
#9684200
0!
#9701908
1!
#9719616
0!
#9733220
r9733.219999999999 )
1#
#9737324
1!
#9755032
0!
#9772740
1!
#9774885
1$
#9790448
0!
#9808156
1!
#9825864
0!
#9843572
1!
#9861280
0!
#9874885
0#
#9878988
1!
#9896696
0!
#9914404
1!
#9916550
0$
#9932112
0!
#9949820
1!
#9967528
0!
#9985236
1!
#10002944
0!
#10016550
r10016.55 )
1#
#10020652
1!
#10038360
0!
#10056068
1!
#10058215
1$
#10073776
0!
#10091484
1!
#10109192
0!
#10126900
1!
#10144608
0!
#10158215
0#
#10162316
1!
#10180024
0!
#10197732
1!
#10199880
0$
#10215440
0!
#10233148
1!
#10250856
0!
#10268564
1!
#10286272
0!
#10299880
r10299.88 )
1#
#10303980
1!
#10321688
0!
#10339396
1!
#10341545
1$
#10357104
0!
#10374812
1!
#10392520
0!
#10410228
1!
#10427936
0!
#10441545
0#
#10445644
1!
#10463352
0!
#10481060
1!
#10483210
0$
#10498768
0!
#10516476
1!
#10534184
0!
#10551892
1!
#10569600
0!
#10583210
r10583.21 )
1#
#10587308
1!
#10605016
0!
#10622724
1!
#10624875
1$
#10640432
0!
#10658140
1!
#10675848
0!
#10693556
1!
#10711264
0!
#10724875
0#
#10728972
1!
#10746680
0!
#10764388
1!
#10766540
0$
#10782096
0!
#10799804
1!
#10817512
0!
#10835220
1!
#10852928
0!
#10866540
r10866.54 )
r35.41625000000022 *
r283.3300000000017 +
1#
#10870636
1!
#10888344
0!
#10906052
1!
#10908205
1$
#10923760
0!
#10941468
1!
#10959176
0!
#10976884
1!
#10994592
0!
#11008205
0#
#11012300
1!
#11030008
0!
#11047716
1!
#11049870
0$
#11065424
0!
#11083132
1!
#11100840
0!
#11118548
1!
#11136256
0!
#11149870
r11149.87 )
r35.41624999999999 *
r283.3299999999999 +
1#
#11153964
1!
#11171672
0!
#11189380
1!
#11191535
1$
#11207088
0!
#11224796
1!
#11242504
0!
#11260212
1!
#11277920
0!
#11291535
0#
#11295628
1!
#11313336
0!
#11331044
1!
#11333200
0$
#11348752
0!
#11366460
1!
#11384168
0!
#11401876
1!
#11419584
0!
#11433200
r11433.2 )
1#
#11437292
1!
#11455000
0!
#11472708
1!
#11474865
1$
#11490416
0!
#11508124
1!
#11525832
0!
#11543540
1!
#11561248
0!
#11574865
0#
#11578956
1!
#11596664
0!
#11614372
1!
#11616530
0$
#11632080
0!
#11649788
1!
#11667496
0!
#11685204
1!
#11702912
0!
#11716530
r11716.53 )
1#
#11720620
1!
#11738328
0!
#11756036
1!
#11758195
1$
#11773744
0!
#11791452
1!
#11809160
0!
#11826868
1!
#11844576
0!
#11858195
0#
#11862284
1!
#11879992
0!
#11897700
1!
#11899860
0$
#11915408
0!
#11933116
1!
#11950824
0!
#11968532
1!
#11986240
0!
#11999860
r11999.86 )
1#
#12003948
1!
#12021656
0!
#12039364
1!
#12041525
1$
#12057072
0!
#12074780
1!
#12092488
0!
#12110196
1!
#12127904
0!
#12141525
0#
#12145612
1!
#12163320
0!
#12181028
1!
#12183190
0$
#12198736
0!
#12216444
1!
#12234152
0!
#12251860
1!
#12269568
0!
#12283190
r12283.19 )
1#
#12287276
1!
#12304984
0!
#12322692
1!
#12324855
1$
#12340400
0!
#12358108
1!
#12375816
0!
#12393524
1!
#12411232
0!
#12424855
0#
#12428940
1!
#12446648
0!
#12464356
1!
#12466520
0$
#12482064
0!
#12499772
1!
#12517480
0!
#12535188
1!
#12552896
0!
#12566520
r12566.52 )
1#
#12570604
1!
#12588312
0!
#12606020
1!
#12608185
1$
#12623728
0!
#12641436
1!
#12659144
0!
#12676852
1!
#12694560
0!
#12708185
0#
#12712268
1!
#12729976
0!
#12747684
1!
#12749850
0$
#12765392
0!
#12783100
1!
#12800808
0!
#12818516
1!
#12836224
0!
#12849850
r12849.85 )
1#
#12853932
1!
#12871640
0!
#12889348
1!
#12891515
1$
#12907056
0!
#12924764
1!
#12942472
0!
#12960180
1!
#12977888
0!
#12991515
0#
#12995596
1!
#13013304
0!
#13031012
1!
#13033180
0$
#13048720
0!
#13066428
1!
#13084136
0!
#13101844
1!
#13119552
0!
#13133180
r13133.18 )
1#
#13137260
1!
#13154968
0!
#13172676
1!
#13174845
1$
#13190384
0!
#13208092
1!
#13225800
0!
#13243508
1!
#13261216
0!
#13274845
0#
#13278924
1!
#13296632
0!
#13314340
1!
#13316510
0$
#13332048
0!
#13349756
1!
#13367464
0!
#13385172
1!
#13402880
0!
#13416510
r13416.51 )
1#
#13420588
1!
#13438296
0!
#13456004
1!
#13458175
1$
#13473712
0!
#13491420
1!
#13509128
0!
#13526836
1!
#13544544
0!
#13558175
0#
#13562252
1!
#13579960
0!
#13597668
1!
#13599840
0$
#13615376
0!
#13633084
1!
#13650792
0!
#13668500
1!
#13686208
0!
#13699840
r13699.84 )
1#
#13703916
1!
#13721624
0!
#13739332
1!
#13741505
1$
#13757040
0!
#13774748
1!
#13792456
0!
#13810164
1!
#13827872
0!
#13841505
0#
#13845580
1!
#13863288
0!
#13880996
1!
#13883170
0$
#13898704
0!
#13916412
1!
#13934120
0!
#13951828
1!
#13969536
0!
#13983170
r13983.17 )
1#
#13987244
1!
#14004952
0!
#14022660
1!
#14024835
1$
#14040368
0!
#14058076
1!
#14075784
0!
#14093492
1!
#14111200
0!
#14124835
0#
#14128908
1!
#14146616
0!
#14164324
1!
#14166500
0$
#14182032
0!
#14199740
1!
#14217448
0!
#14235156
1!
#14252864
0!
#14266500
r14266.5 )
1#
#14270572
1!
#14288280
0!
#14305988
1!
#14308165
1$
#14323696
0!
#14341404
1!
#14359112
0!
#14376820
1!
#14394528
0!
#14408165
0#
#14412236
1!
#14429944
0!
#14447652
1!
#14449830
0$
#14465360
0!
#14483068
1!
#14500776
0!
#14518484
1!
#14536192
0!
#14549830
r14549.83 )
1#
#14553900
1!
#14571608
0!
#14589316
1!
#14591495
1$
#14607024
0!
#14624732
1!
#14642440
0!
#14660148
1!
#14677856
0!
#14691495
0#
#14695564
1!
#14713272
0!
#14730980
1!
#14733160
0$
#14748688
0!
#14766396
1!
#14784104
0!
#14801812
1!
#14819520
0!
#14833160
r14833.16 )
1#
#14837228
1!
#14854936
0!
#14872644
1!
#14874825
1$
#14890352
0!
#14908060
1!
#14925768
0!
#14943476
1!
#14961184
0!
#14974825
0#
#14978892
1!
#14996600
0!
#15014308
1!
#15016490
0$
#15032016
0!
#15049724
1!
#15067432
0!
#15085140
1!
#15102848
0!
#15116490
r15116.49 )
1#
#15120556
1!
#15138264
0!
#15155972
1!
#15158155
1$
#15173680
0!
#15191388
1!
#15209096
0!
#15226804
1!
#15244512
0!
#15258155
0#
#15262220
1!
#15279928
0!
#15297636
1!
#15299820
0$
#15315344
0!
#15333052
1!
#15350760
0!
#15368468
1!
#15386176
0!
#15399820
r15399.82 )
1#
#15403884
1!
#15421592
0!
#15439300
1!
#15441485
1$
#15457008
0!
#15474716
1!
#15492424
0!
#15510132
1!
#15527840
0!
#15541485
0#
#15545548
1!
#15563256
0!
#15580964
1!
#15583150
0$
#15598672
0!
#15616380
1!
#15634088
0!
#15651796
1!
#15669504
0!
#15683150
r15683.15 )
1#
#15687212
1!
#15704920
0!
#15722628
1!
#15724815
1$
#15740336
0!
#15758044
1!
#15775752
0!
#15793460
1!
#15811168
0!
#15824815
0#
#15828876
1!
#15846584
0!
#15864292
1!
#15866480
0$
#15882000
0!
#15899708
1!
#15917416
0!
#15935124
1!
#15952832
0!
#15966480
r15966.48 )
1#
#15970540
1!
#15988248
0!
#16005956
1!
#16008145
1$
#16023664
0!
#16041372
1!
#16059080
0!
#16076788
1!
#16094496
0!
#16108145
0#
#16112204
1!
#16129912
0!
#16147620
1!
#16149810
0$
#16165328
0!
#16183036
1!
#16200744
0!
#16218452
1!
#16236160
0!
#16249810
r16249.81 )
1#
#16253868
1!
#16271576
0!
#16289284
1!
#16291475
1$
#16306992
0!
#16324700
1!
#16342408
0!
#16360116
1!
#16377824
0!
#16391475
0#
#16395532
1!
#16413240
0!
#16430948
1!
#16433140
0$
#16448656
0!
#16466364
1!
#16484072
0!
#16501780
1!
#16519488
0!
#16533140
r16533.14 )
1#
#16537196
1!
#16554904
0!
#16572612
1!
#16574805
1$
#16590320
0!
#16608028
1!
#16625736
0!
#16643444
1!
#16661152
0!
#16674805
0#
#16678860
1!
#16696568
0!
#16714276
1!
#16716470
0$
#16731984
0!
#16749692
1!
#16767400
0!
#16785108
1!
#16802816
0!
#16816470
r16816.47 )
r35.41625000000022 *
r283.3300000000017 +
1#
#16820524
1!
#16838232
0!
#16855940
1!
#16858135
1$
#16873648
0!
#16891356
1!
#16909064
0!
#16926772
1!
#16944480
0!
#16958135
0#
#16962188
1!
#16979896
0!
#16997604
1!
#16999800
0$
#17015312
0!
#17033020
1!
#17050728
0!
#17068436
1!
#17086144
0!
#17099800
r17099.8 )
r35.41624999999976 *
r283.3299999999981 +
1#
#17103852
1!
#17121560
0!
#17139268
1!
#17141465
1$
#17156976
0!
#17174684
1!
#17192392
0!
#17210100
1!
#17227808
0!
#17241465
0#
#17245516
1!
#17263224
0!
#17280932
1!
#17283130
0$
#17298640
0!
#17316348
1!
#17334056
0!
#17351764
1!
#17369472
0!
#17383130
r17383.13 )
r35.41625000000022 *
r283.3300000000017 +
1#
#17387180
1!
#17404888
0!
#17422596
1!
#17424795
1$
#17440304
0!
#17458012
1!
#17475720
0!
#17493428
1!
#17511136
0!
#17524795
0#
#17528844
1!
#17546552
0!
#17564260
1!
#17566460
0$
#17581968
0!
#17599676
1!
#17617384
0!
#17635092
1!
#17652800
0!
#17666460
r17666.46 )
r35.41624999999976 *
r283.3299999999981 +
1#
#17670508
1!
#17688216
0!
#17705924
1!
#17708125
1$
#17723632
0!
#17741340
1!
#17759048
0!
#17776756
1!
#17794464
0!
#17808125
0#
#17812172
1!
#17829880
0!
#17847588
1!
#17849790
0$
#17865296
0!
#17883004
1!
#17900712
0!
#17918420
1!
#17936128
0!
#17949790
r17949.79 )
r35.41625000000022 *
r283.3300000000017 +
1#
#17953836
1!
#17971544
0!
#17989252
1!
#17991455
1$
#18006960
0!
#18024668
1!
#18042376
0!
#18060084
1!
#18077792
0!
#18091455
0#
#18095500
1!
#18113208
0!
#18130916
1!
#18133120
0$
#18148624
0!
#18166332
1!
#18184040
0!
#18201748
1!
#18219456
0!
#18233120
r18233.12 )
r35.41624999999976 *
r283.3299999999981 +
1#
#18237164
1!
#18254872
0!
#18272580
1!
#18274785
1$
#18290288
0!
#18307996
1!
#18325704
0!
#18343412
1!
#18361120
0!
#18374785
0#
#18378828
1!
#18396536
0!
#18414244
1!
#18416450
0$
#18431952
0!
#18449660
1!
#18467368
0!
#18485076
1!
#18502784
0!
#18516450
r18516.45 )
r35.41625000000022 *
r283.3300000000017 +
1#
#18520492
1!
#18538200
0!
#18555908
1!
#18558115
1$
#18573616
0!
#18591324
1!
#18609032
0!
#18626740
1!
#18644448
0!
#18658115
0#
#18662156
1!
#18679864
0!
#18697572
1!
#18699780
0$
#18715280
0!
#18732988
1!
#18750696
0!
#18768404
1!
#18786112
0!
#18799780
r18799.78 )
r35.41624999999976 *
r283.3299999999981 +
1#
#18803820
1!
#18821528
0!
#18839236
1!
#18841445
1$
#18856944
0!
#18874652
1!
#18892360
0!
#18910068
1!
#18927776
0!
#18941445
0#
#18945484
1!
#18963192
0!
#18980900
1!
#18983110
0$
#18998608
0!
#19016316
1!
#19034024
0!
#19051732
1!
#19069440
0!
#19083110
r19083.11 )
r35.41625000000022 *
r283.3300000000017 +
1#
#19087148
1!
#19104856
0!
#19122564
1!
#19124775
1$
#19140272
0!
#19157980
1!
#19175688
0!
#19193396
1!
#19211104
0!
#19224775
0#
#19228812
1!
#19246520
0!
#19264228
1!
#19266440
0$
#19281936
0!
#19299644
1!
#19317352
0!
#19335060
1!
#19352768
0!
#19366440
r19366.44 )
r35.41624999999976 *
r283.3299999999981 +
1#
#19370476
1!
#19388184
0!
#19405892
1!
#19408105
1$
#19423600
0!
#19441308
1!
#19459016
0!
#19476724
1!
#19494432
0!
#19508105
0#
#19512140
1!
#19529848
0!
#19547556
1!
#19549770
0$
#19565264
0!
#19582972
1!
#19600680
0!
#19618388
1!
#19636096
0!
#19649770
r19649.77 )
r35.41625000000022 *
r283.3300000000017 +
1#
#19653804
1!
#19671512
0!
#19689220
1!
#19691435
1$
#19706928
0!
#19724636
1!
#19742344
0!
#19760052
1!
#19777760
0!
#19791435
0#
#19795468
1!
#19813176
0!
#19830884
1!
#19833100
0$
#19848592
0!
#19866300
1!
#19884008
0!
#19901716
1!
#19919424
0!
#19933100
r19933.1 )
r35.41624999999976 *
r283.3299999999981 +
1#
#19937132
1!
#19954840
0!
#19972548
1!
#19974765
1$
#19990256
0!
#20007964
1!
#20025672
0!
#20043380
1!
#20061088
0!
#20074765
0#
#20078796
1!
#20096504
0!
#20114212
1!
#20116430
0$
#20131920
0!
#20149628
1!
#20167336
0!
#20185044
1!
#20202752
0!
#20216430
r20216.43 )
r35.41625000000022 *
r283.3300000000017 +
1#
#20220460
1!
#20238168
0!
#20255876
1!
#20258095
1$
#20273584
0!
#20291292
1!
#20309000
0!
#20326708
1!
#20344416
0!
#20358095
0#
#20362124
1!
#20379832
0!
#20397540
1!
#20399760
0$
#20415248
0!
#20432956
1!
#20450664
0!
#20468372
1!
#20486080
0!
#20499760
r20499.76 )
r35.41624999999976 *
r283.3299999999981 +
1#
#20503788
1!
#20521496
0!
#20539204
1!
#20541425
1$
#20556912
0!
#20574620
1!
#20592328
0!
#20610036
1!
#20627744
0!
#20641425
0#
#20645452
1!
#20663160
0!
#20680868
1!
#20683090
0$
#20698576
0!
#20716284
1!
#20733992
0!
#20751700
1!
#20769408
0!
#20783090
r20783.09 )
r35.41625000000022 *
r283.3300000000017 +
1#
#20787116
1!
#20804824
0!
#20822532
1!
#20824755
1$
#20840240
0!
#20857948
1!
#20875656
0!
#20893364
1!
#20911072
0!
#20924755
0#
#20928780
1!
#20946488
0!
#20964196
1!
#20966420
0$
#20981904
0!
#20999612
1!
#21017320
0!
#21035028
1!
#21052736
0!
#21066420
r21066.42 )
r35.41624999999976 *
r283.3299999999981 +
1#
#21070444
1!
#21088152
0!
#21105860
1!
#21108085
1$
#21123568
0!
#21141276
1!
#21158984
0!
#21176692
1!
#21194400
0!
#21208085
0#
#21212108
1!
#21229816
0!
#21247524
1!
#21249750
0$
#21265232
0!
#21282940
1!
#21300648
0!
#21318356
1!
#21336064
0!
#21349750
r21349.75 )
r35.41625000000022 *
r283.3300000000017 +
1#
#21353772
1!
#21371480
0!
#21389188
1!
#21391415
1$
#21406896
0!
#21424604
1!
#21442312
0!
#21460020
1!
#21477728
0!
#21491415
0#
#21495436
1!
#21513144
0!
#21530852
1!
#21533080
0$
#21548560
0!
#21566268
1!
#21583976
0!
#21601684
1!
#21619392
0!
#21633080
r21633.08 )
1#
#21637100
1!
#21654808
0!
#21672516
1!
#21674745
1$
#21690224
0!
#21707932
1!
#21725640
0!
#21743348
1!
#21761056
0!
#21774745
0#
#21778764
1!
#21796472
0!
#21814180
1!
#21816410
0$
#21831888
0!
#21849596
1!
#21867304
0!
#21885012
1!
#21902720
0!
